hepinfo/__init__.py
hepinfo/util.py
hepinfo/models/BaseModel.py
hepinfo/models/BinaryMI.py
hepinfo/models/DebiasClassifier.py
hepinfo/models/GradReverse.py
hepinfo/models/HBernoulliLayer.py
hepinfo/models/MiVAE.py
hepinfo/models/QuantFlow.py
hepinfo/models/__init__.py
hepinfo/models/qkerasV3.py
hepinfo-0.1.4.dist-info/LICENSE
hepinfo-0.1.4.dist-info/METADATA
hepinfo-0.1.4.dist-info/WHEEL
hepinfo-0.1.4.dist-info/top_level.txt
hepinfo-0.1.4.dist-info/RECORD
