Metadata-Version: 2.2
Name: hepinfo
Version: 0.1.4
Summary: Mutual Information techniques for decorrelation of physics data
Author-email: Marius Köppel <mkoepp@phys.ethz.ch>
Project-URL: Homepage, https://github.com/makoeppel/hepinfo/
Project-URL: Issues, https://github.com/makoeppel/hepinfo/issues
Classifier: License :: OSI Approved :: MIT License
Classifier: Operating System :: OS Independent
Classifier: Programming Language :: Python :: 3 :: Only
Classifier: Programming Language :: Python :: 3.10
Classifier: Programming Language :: Python :: 3.11
Classifier: Programming Language :: Python :: 3.12
Classifier: Programming Language :: Python :: 3.13
Requires-Python: >=3.10
License-File: LICENSE
